README.rst
setup.py
dbimage/__init__.py
dbimage/convert.py
dbimage/info.py
dbimage/io.py
dbimage.egg-info/PKG-INFO
dbimage.egg-info/SOURCES.txt
dbimage.egg-info/dependency_links.txt
dbimage.egg-info/entry_points.txt
dbimage.egg-info/not-zip-safe
dbimage.egg-info/requires.txt
dbimage.egg-info/top_level.txt