Metadata-Version: 1.0
Name: dbimage
Version: 0.1.1
Summary: dtoolbioimage image format
Home-page: https://github.com/JIC-Image-Analysis/dbimage
Author: Matthew Hartley
Author-email: Matthew.Hartley@jic.ac.uk
License: MIT
Platform: UNKNOWN
